api/__init__.py
api/celeryconfig.py
bunkatopics/__init__.py
bunkatopics/_bunkatopics.py
bunkatopics/datamodel.py
bunkatopics/logging.py
bunkatopics/utils.py
bunkatopics/bourdieu/__init__.py
bunkatopics/bourdieu/bourdieu_api.py
bunkatopics/bourdieu/bourdieu_one_dimension.py
bunkatopics/bourdieu/bourdieu_visualizer.py
bunkatopics/serveur/__init__.py
bunkatopics/serveur/server_utils.py
bunkatopics/topic_modeling/__init__.py
bunkatopics/topic_modeling/coherence_calculator.py
bunkatopics/topic_modeling/document_topic_ranker.py
bunkatopics/topic_modeling/elbow_method.py
bunkatopics/topic_modeling/legacy.py
bunkatopics/topic_modeling/llm_topic_representation.py
bunkatopics/topic_modeling/prompt_generator.py
bunkatopics/topic_modeling/term_extractor.py
bunkatopics/topic_modeling/topic_model_builder.py
bunkatopics/topic_modeling/topic_utils.py
bunkatopics/topic_modeling/utils.py
bunkatopics/visualization/__init__.py
bunkatopics/visualization/convex_hull_plotter.py
bunkatopics/visualization/query_visualizer.py
bunkatopics/visualization/topic_explainer.py
bunkatopics/visualization/topic_visualizer.py
bunkatopics/visualization/visualization_utils.py
bunkatopics-0.46.1.dist-info/LICENSE.txt
bunkatopics-0.46.1.dist-info/METADATA
bunkatopics-0.46.1.dist-info/WHEEL
bunkatopics-0.46.1.dist-info/top_level.txt
bunkatopics-0.46.1.dist-info/RECORD
