Metadata-Version: 2.1
Name: bunkatopics
Version: 0.46.1
Summary: Bunkatopics is a Topic Modeling package and Exploration Module
Home-page: https://github.com/charlesdedampierre/BunkaTopics
Author: Charles de Dampierre
Author-email: charlesdedampierre@gmail.com
Project-URL: Source code, https://github.com/charlesdedampierre/BunkaTopics
Project-URL: Documentation, https://charlesdedampierre.github.io/BunkaTopics/
Project-URL: Issue Tracker, https://github.com/charlesdedampierre/BunkaTopics/issues
Keywords: AI Topic Modeling Visualization Exploration Fine-tuning
Classifier: Programming Language :: Python
Classifier: Intended Audience :: Science/Research
Classifier: Intended Audience :: Developers
Classifier: Topic :: Scientific/Engineering :: Artificial Intelligence
Classifier: License :: OSI Approved :: Apache Software License
Classifier: Topic :: Scientific/Engineering
Classifier: Operating System :: Microsoft :: Windows
Classifier: Operating System :: POSIX
Classifier: Operating System :: Unix
Classifier: Operating System :: MacOS
Classifier: Programming Language :: Python :: 3.9
Classifier: Programming Language :: Python :: 3.10
Classifier: Programming Language :: Python :: 3.11
Requires-Python: >=3.9
License-File: LICENSE.txt
Requires-Dist: pandas >=2.0.2
Requires-Dist: umap-learn >=0.5.3
Requires-Dist: pydantic >=2.5.3
Requires-Dist: loguru >=0.7.0
Requires-Dist: langchain >=0.0.206
Requires-Dist: plotly >=5.15.0
Requires-Dist: textacy >=0.13.0
Requires-Dist: gensim >=4.3.1
Requires-Dist: sentence-transformers >=2.7.0
Requires-Dist: openai >=0.28.0
Requires-Dist: python-dotenv >=1.0.0
Requires-Dist: matplotlib >=3.7.2
Requires-Dist: datasets >=2.14.5
Requires-Dist: psutil >=5.9.7
Requires-Dist: colorlog >=6.8.0
Requires-Dist: langchain-openai
Requires-Dist: ipython
Requires-Dist: ipywidgets >=8.1.2
Requires-Dist: jsonlines >=4.0.0
Requires-Dist: pyod >=1.1.3
Requires-Dist: FlagEmbedding >=1.2.8
Requires-Dist: tiktoken ==0.6.0
Requires-Dist: langdetect >=1.0.9
Provides-Extra: dev
Requires-Dist: nbformat >=4.2.0 ; extra == 'dev'
Requires-Dist: nbconvert >=7.16.3 ; extra == 'dev'
Requires-Dist: jupyter >=1.00 ; extra == 'dev'
Requires-Dist: black ~=23.0 ; extra == 'dev'
Requires-Dist: isort ~=5.0 ; extra == 'dev'
Requires-Dist: twine ~=4.0 ; extra == 'dev'
Requires-Dist: wheel ; extra == 'dev'
Requires-Dist: kaleido ; extra == 'dev'
Requires-Dist: flake8 ; extra == 'dev'
Requires-Dist: mkdocs >=1.1.2 ; extra == 'dev'
Requires-Dist: mkdocs-material >=8.1.4 ; extra == 'dev'
Requires-Dist: mkdocstrings >=0.24.0 ; extra == 'dev'
Requires-Dist: mkdocstrings-python >=1.8.0 ; extra == 'dev'
Provides-Extra: docs
Requires-Dist: mkdocs >=1.1.2 ; extra == 'docs'
Requires-Dist: mkdocs-material >=8.1.4 ; extra == 'docs'
Requires-Dist: mkdocstrings >=0.24.0 ; extra == 'docs'
Requires-Dist: mkdocstrings-python >=1.8.0 ; extra == 'docs'
Provides-Extra: format
Requires-Dist: black ~=23.0 ; extra == 'format'
Requires-Dist: isort ~=5.0 ; extra == 'format'
Requires-Dist: twine ~=4.0 ; extra == 'format'
Requires-Dist: wheel ; extra == 'format'
Requires-Dist: kaleido ; extra == 'format'
Requires-Dist: flake8 ; extra == 'format'
Provides-Extra: test
Requires-Dist: nbformat >=4.2.0 ; extra == 'test'
Requires-Dist: nbconvert >=7.16.3 ; extra == 'test'
Requires-Dist: jupyter >=1.00 ; extra == 'test'
